ARIESian/ARIES.py
ARIESian/__init__.py
ARIESian-1.0.12.dist-info/LICENSE
ARIESian-1.0.12.dist-info/METADATA
ARIESian-1.0.12.dist-info/WHEEL
ARIESian-1.0.12.dist-info/top_level.txt
ARIESian-1.0.12.dist-info/RECORD
