Metadata-Version: 2.1
Name: ARIESian
Version: 1.0.12
Summary: Testing ARIES optical data reduction pipeline
Home-page: UNKNOWN
Author: Gurpreet Singh
Author-email: <gravity.sweg@gmail.com>
License: UNKNOWN
Keywords: python,first package
Platform: UNKNOWN
Classifier: Development Status :: 3 - Alpha
Classifier: Intended Audience :: Education
Classifier: Programming Language :: Python :: 2
Classifier: Programming Language :: Python :: 3
License-File: LICENSE
